{"title": "\u6d77\uff1a\u53e6\u4e00\u4e2a\u672a\u77e5\u7684\u5b87\u5b99\uff08\u767e\u4e07\u9500\u91cf\u5c0f\u8bf4\u300a\u7fa4\u300b\u4e4b\u59ca\u59b9\u7bc7\uff0c\u9996\u521b\u4ee5\u60ca\u609a\u5c0f\u8bf4\u624b\u6cd5\u523b\u753b45\u4ebf\u5e74\u6d77\u6d0b\u53f2\uff01\uff09", "subtitle": "\u6d77\uff1a\u53e6\u4e00\u4e2a\u672a\u77e5\u7684\u5b87\u5b99\uff08\u767e\u4e07\u9500\u91cf\u5c0f\u8bf4\u300a\u7fa4\u300b\u4e4b\u59ca\u59b9\u7bc7\uff0c\u9996\u521b\u4ee5\u60ca\u609a\u5c0f\u8bf4\u624b\u6cd5\u523b\u753b45\u4ebf\u5e74\u6d77\u6d0b\u53f2\uff01\uff09", "author": "\u5f17\u5170\u514b\u00b7\u65bd\u8328\u5ef7", "type": "book", "source": "clippings", "book_id": "34706410", "last_highlight_date": "2019-04-19", "isbn": "", "location": "", "status": "TBR"}